functions/__init__.py
functions/functions.py
traffic_crashes-0.1.0.dist-info/METADATA
traffic_crashes-0.1.0.dist-info/WHEEL
traffic_crashes-0.1.0.dist-info/top_level.txt
traffic_crashes-0.1.0.dist-info/RECORD
