Metadata-Version: 2.1
Name: traffic-crashes
Version: 0.1.0
Summary: PSYC 40650 Collaborative Project - Traffic Crashes in Chicago
Home-page: https://bitbucket.org/ytbai/traffic_crashes/src/master/
Author: PSYC 40650
Author-email: jadynpark@uchicago.edu
License: UNKNOWN
Platform: UNKNOWN
Requires-Dist: pandas
Requires-Dist: matplotlib
Requires-Dist: numpy
Requires-Dist: scipy
Requires-Dist: scikit-learn
Requires-Dist: bokeh (==2.2.2)
Requires-Dist: seaborn
Requires-Dist: qgrid
Requires-Dist: geoplot
